quartoogle/__init__.py
quartoogle/api.py
quartoogle/cli.py
quartoogle/constants.py
quartoogle/gdrive.py
quartoogle/quarto.py
quartoogle-0.1.2.dist-info/METADATA
quartoogle-0.1.2.dist-info/WHEEL
quartoogle-0.1.2.dist-info/entry_points.txt
quartoogle-0.1.2.dist-info/licenses/LICENSE
quartoogle-0.1.2.dist-info/RECORD
