Metadata-Version: 2.4
Name: quartoogle
Version: 0.1.2
Summary: Compile quarto docs directly to google drive
Author: Zach Kurtz
License: MIT
License-File: LICENSE
Requires-Python: >=3.12
Requires-Dist: attrs>=24.0.0
Requires-Dist: click>=8.0.0
Requires-Dist: google-api-python-client>=2.0.0
Requires-Dist: google-auth-httplib2>=0.1.0
Requires-Dist: google-auth-oauthlib>=1.0.0
Requires-Dist: google-auth>=2.0.0
Requires-Dist: jupyter>=1.1.1
Requires-Dist: quarto>=0.1.0
